robot/tasks.py
robot_tasks-0.2.1.dist-info/METADATA
robot_tasks-0.2.1.dist-info/WHEEL
robot_tasks-0.2.1.dist-info/licenses/AUTHORS.rst
robot_tasks-0.2.1.dist-info/licenses/LICENSE
robot_tasks-0.2.1.dist-info/RECORD
