Metadata-Version: 2.4
Name: robot-tasks
Version: 0.2.1
Summary: Simple task library using asyncio.
Project-URL: Documentation, https://github.com/fmorton/robot-tasks#readme
Project-URL: Issues, https://github.com/fmorton/robot-tasks/issues
Project-URL: Source, https://github.com/fmorton/robot-tasks
Author-email: Frank Morton <fmorton@mac.com>
License-Expression: MIT
License-File: AUTHORS.rst
License-File: LICENSE
Classifier: Development Status :: 4 - Beta
Classifier: Programming Language :: Python
Classifier: Programming Language :: Python :: 3.9
Classifier: Programming Language :: Python :: 3.10
Classifier: Programming Language :: Python :: 3.11
Classifier: Programming Language :: Python :: 3.12
Classifier: Programming Language :: Python :: 3.13
Classifier: Programming Language :: Python :: Implementation :: CPython
Classifier: Programming Language :: Python :: Implementation :: PyPy
Requires-Python: >=3.9
Provides-Extra: dev
Requires-Dist: black; extra == 'dev'
Requires-Dist: flake8; extra == 'dev'
Requires-Dist: pytest; extra == 'dev'
Requires-Dist: pytest-mock; extra == 'dev'
